controlpy/analysis.py
controlpy/synthesis.py
controlpy/__init__.py
controlpy-0.0.0.dev1.dist-info/DESCRIPTION.rst
controlpy-0.0.0.dev1.dist-info/METADATA
controlpy-0.0.0.dev1.dist-info/metadata.json
controlpy-0.0.0.dev1.dist-info/RECORD
controlpy-0.0.0.dev1.dist-info/top_level.txt
controlpy-0.0.0.dev1.dist-info/WHEEL
