Metadata-Version: 2.0
Name: controlpy
Version: 0.0.0.dev1
Summary: Python control library
Home-page: http://github.com/markwmuller/controlpy
Author: Mark W. Mueller
Author-email: mwm@mwm.im
License: GPL V3
Keywords: control lqr robust H2 Hinf Hinfinity
Platform: UNKNOWN
Classifier: Development Status :: 3 - Alpha
Classifier: Programming Language :: Python :: 2.7
